LICENSE
MANIFEST.in
README.rst
requirements.txt
setup.py
bootstrap4_nav/__init__.py
bootstrap4_nav/__meta__.py
bootstrap4_nav/context_processors.py
bootstrap4_nav/models.py
bootstrap4_nav/settings.py
bootstrap4_nav/utils.py
bootstrap4_nav/migrations/__init__.py
bootstrap4_nav/static/bootstrap4_nav/bootstrap4_nav.css
bootstrap4_nav/static/bootstrap4_nav/bootstrap4_nav.js
bootstrap4_nav/templates/bootstrap4_nav/400.html
bootstrap4_nav/templates/bootstrap4_nav/403.html
bootstrap4_nav/templates/bootstrap4_nav/404.html
bootstrap4_nav/templates/bootstrap4_nav/500.html
bootstrap4_nav/templates/bootstrap4_nav/base.html
bootstrap4_nav/templates/bootstrap4_nav/begin_body.html
bootstrap4_nav/templates/bootstrap4_nav/end_body.html
bootstrap4_nav/templates/bootstrap4_nav/footer.html
bootstrap4_nav/templates/bootstrap4_nav/head.html
bootstrap4_nav/templates/bootstrap4_nav/messages.html
bootstrap4_nav/templates/bootstrap4_nav/navbar.html
bootstrap4_nav/templates/bootstrap4_nav/navbar_items.html
bootstrap4_nav/templates/bootstrap4_nav/sidenav.html
bootstrap4_nav/templates/bootstrap4_nav/sidenav_items.html
bootstrap4_nav/templatetags/__init__.py
bootstrap4_nav/templatetags/bootstrap4_nav.py
django_bootstrap4_nav.egg-info/PKG-INFO
django_bootstrap4_nav.egg-info/SOURCES.txt
django_bootstrap4_nav.egg-info/dependency_links.txt
django_bootstrap4_nav.egg-info/requires.txt
django_bootstrap4_nav.egg-info/top_level.txt