Metadata-Version: 1.1
Name: django-bootstrap4-nav
Version: 0.0.1
Summary: Bootstrap template support for Django projects
Home-page: https://github.com/justengel-django/django_bootstrap4_nav
Author: Justin Engel
Author-email: jtengel08@gmail.com
License: Proprietary
Download-URL: https://github.com/justengel-django/django_bootstrap4_nav/archive/v0.0.1.tar.gz
Keywords: Django Bootstrap4 Nav CSS
Platform: any
Classifier: Programming Language :: Python
Classifier: Programming Language :: Python :: 3
Classifier: Operating System :: OS Independent
Classifier: Framework :: Django :: 2.0
Classifier: License :: OSI Approved :: MIT License
